MANIFEST.in
pyproject.toml
setup.cfg
setup.py
versioneer.py
./RDPMSpecIdentifier/__init__.py
./RDPMSpecIdentifier/_version.py
./RDPMSpecIdentifier/datastructures.py
./RDPMSpecIdentifier/executables.py
./RDPMSpecIdentifier/plots.py
./RDPMSpecIdentifier/tests/test_dash.py
./RDPMSpecIdentifier/tests/test_datastructures.py
./RDPMSpecIdentifier/visualize/__init__.py
./RDPMSpecIdentifier/visualize/appDefinition.py
./RDPMSpecIdentifier/visualize/clusterAndSettings.py
./RDPMSpecIdentifier/visualize/dataTable.py
./RDPMSpecIdentifier/visualize/distributionAndHeatmap.py
./RDPMSpecIdentifier/visualize/modals.py
./RDPMSpecIdentifier/visualize/runApp.py
./RDPMSpecIdentifier/visualize/staticContent.py
./RDPMSpecIdentifier/visualize/assets/01_style.css
./RDPMSpecIdentifier/visualize/assets/RDPMSpecIdentifier_dark.svg
./RDPMSpecIdentifier/visualize/assets/RDPMSpecIdentifier_dark_no_text.svg
./RDPMSpecIdentifier/visualize/assets/RDPMSpecIdentifier_light_no_text.svg
./RDPMSpecIdentifier/visualize/assets/additional.js
./RDPMSpecIdentifier/visualize/assets/favicon.ico
./RDPMSpecIdentifier/visualize/assets/index.html
./RDPMSpecIdentifier/visualize/callbacks/__init__.py
./RDPMSpecIdentifier/visualize/callbacks/mainCallbacks.py
./RDPMSpecIdentifier/visualize/callbacks/modalCallbacks.py
./RDPMSpecIdentifier/visualize/callbacks/plotCallbacks.py
./RDPMSpecIdentifier/visualize/callbacks/tableCallbacks.py
./RDPMSpecIdentifier/visualize/pages/__init__.py
./RDPMSpecIdentifier/visualize/pages/analysis_page.py
./RDPMSpecIdentifier/visualize/pages/upload_page.py
RDPMSpecIdentifier/_version.py
RDPMSpecIdentifier/executables.py
RDPMSpecIdentifier.egg-info/PKG-INFO
RDPMSpecIdentifier.egg-info/SOURCES.txt
RDPMSpecIdentifier.egg-info/dependency_links.txt
RDPMSpecIdentifier.egg-info/entry_points.txt
RDPMSpecIdentifier.egg-info/requires.txt
RDPMSpecIdentifier.egg-info/top_level.txt
RDPMSpecIdentifier/tests/test_dash.py
RDPMSpecIdentifier/tests/test_datastructures.py
RDPMSpecIdentifier/visualize/assets/01_style.css
docs/build/html/_sphinx_design_static/design-style.1e8bd061cd6da7fc9cf755528e8ffc24.min.css
docs/build/html/_static/args.css
docs/build/html/_static/basic.css
docs/build/html/_static/design-style.1e8bd061cd6da7fc9cf755528e8ffc24.min.css
