Metadata-Version: 2.1
Name: RDPMSpecIdentifier
Version: 0.1.1
Summary: Package for identification of RNA dependent Proteins from mass spec data 
Home-page: https://github.com/domonik/RDPMSpecIdentifier
Author: domonik
Author-email: dominik.rabsch@gmail.com
License: LICENSE
